{"concept:academicprogramatuniversity": 0, "concept:proxyfor": 1, "concept:atdate": 2, "concept:subpartof": 3, "concept:academicfieldsuchasacademicfield": 4, "concept:academicfieldconcernssubject": 5, "concept:synonymfor": 6, "concept:mutualproxyfor": 7, "concept:ismultipleof": 8, "concept:istallerthan": 9, "concept:latitudelongitude": 10, "concept:atlocation": 11, "concept:actorstarredinmovie": 12, "concept:hasspouse": 13, "concept:agentinvolvedwithitem": 14, "concept:agentparticipatedinevent": 15, "concept:personchargedwithcrime": 16, "concept:personhasresidenceingeopoliticallocation": 17, "concept:agentcreated": 18, "concept:haswife": 19, "concept:persondiedincountry": 20, "concept:persondiedatage": 21, "concept:personbelongstoorganization": 22, "concept:personhasjobposition": 23, "concept:personalsoknownas": 24, "concept:worksfor": 25, "concept:agentcontributedtocreativework": 26, "concept:personleadsorganization": 27, "concept:agentcompeteswithagent": 28, "concept:agentactsinlocation": 29, "concept:agentcontrols": 30, "concept:topmemberoforganization": 31, "concept:hashusband": 32, "concept:personleadsgeopoliticalorganization": 33, "concept:personbornincity": 34, "concept:personborninlocation": 35, "concept:parentofperson": 36, "concept:agentcollaborateswithagent": 37, "concept:personhascitizenship": 38, "concept:persongraduatedfromuniversity": 39, "concept:persongraduatedschool": 40, "concept:organizationalsoknownas": 41, "concept:organizationterminatedperson": 42, "concept:objectfoundinscene": 43, "concept:objectpartofobject": 44, "concept:agriculturalproductgrowninlandscapefeatures": 45, "concept:foodcancausedisease": 46, "concept:agriculturalproductincludingagriculturalproduct": 47, "concept:agriculturalproductcontainchemical": 48, "concept:fooddecreasestheriskofdisease": 49, "concept:agriculturalproductcookedwithagriculturalproduct": 50, "concept:agriculturalproductcutintogeometricshape": 51, "concept:agriculturalproducttoattractinsect": 52, "concept:thinghascolor": 53, "concept:agriculturalproductcomingfromvertebrate": 54, "concept:agriculturalproductcamefromcountry": 55, "concept:animalistypeofanimal": 56, "concept:mammalsuchasmammal": 57, "concept:animaleatvegetable": 58, "concept:specializationof": 59, "concept:beveragemadefrombeverage": 60, "concept:beveragecontainsprotein": 61, "concept:agriculturalproductgrowinginstateorprovince": 62, "concept:arthropodcalledarthropod": 63, "concept:animaleatfood": 64, "concept:animalpreyson": 65, "concept:animaldevelopdisease": 66, "concept:thinghasshape": 67, "concept:animalsuchasfish": 68, "concept:airportincity": 69, "concept:buildinglocatedincity": 70, "concept:touristattractionsuchastouristattraction": 71, "concept:attractionofcity": 72, "concept:locationlocatedwithinlocation": 73, "concept:transportationincity": 74, "concept:animalthatfeedoninsect": 75, "concept:animalsuchasinvertebrate": 76, "concept:animalsuchasinsect": 77, "concept:invertebratefeedonfood": 78, "concept:arthropodandotherarthropod": 79, "concept:drugpossiblytreatsphysiologicalcondition": 80, "concept:hassibling": 81, "concept:visualartistartform": 82, "concept:arterycalledartery": 83, "concept:bodypartcontainsbodypart": 84, "concept:politicianrepresentslocation": 85, "concept:politicianusmemberofpoliticalgroup": 86, "concept:politicianusendorsedbypoliticianus": 87, "concept:politicianusholdsoffice": 88, "concept:politicianholdsoffice": 89, "concept:personmovedtostateorprovince": 90, "concept:athleteplayssport": 91, "concept:coachwontrophy": 92, "concept:athleteflyouttosportsteamposition": 93, "concept:athleteinjuredhisbodypart": 94, "concept:athleteplayssportsteamposition": 95, "concept:athleteplaysinleague": 96, "concept:athleteplaysforteam": 97, "concept:athleteledsportsteam": 98, "concept:athletehomestadium": 99, "concept:athletewinsawardtrophytournament": 100, "concept:athletebeatathlete": 101, "concept:coachesinleague": 102, "concept:agentbelongstoorganization": 103, "concept:fatherofperson": 104, "concept:coachesteam": 105, "concept:motherofperson": 106, "concept:riveremptiesintoriver": 107, "concept:hotelincity": 108, "concept:automobilemakerdealersincountry": 109, "concept:automakerproducesmodel": 110, "concept:automobilemakerdealersincity": 111, "concept:automobilemakercardealersinstateorprovince": 112, "concept:hasofficeincountry": 113, "concept:companyeconomicsector": 114, "concept:subpartoforganization": 115, "concept:acquired": 116, "concept:producesproduct": 117, "concept:competeswith": 118, "concept:headquarteredin": 119, "concept:companyalsoknownas": 120, "concept:organizationheadquarteredinstateorprovince": 121, "concept:organizationhiredperson": 122, "concept:hasofficeincity": 123, "concept:organizationheadquarteredincountry": 124, "concept:organizationdissolvedatdate": 125, "concept:organizationheadquarteredincity": 126, "concept:awardtrophytournamentisthechampionshipgameofthenationalsport": 127, "concept:bacteriaisthecausativeagentofphysiologicalcondition": 128, "concept:drughassideeffect": 129, "concept:bakedgoodservedwithbeverage": 130, "concept:organizationacronymhasname": 131, "concept:bankbankincountry": 132, "concept:bankboughtbank": 133, "concept:itemfoundinroom": 134, "concept:parkincity": 135, "concept:bookwriter": 136, "concept:stadiumlocatedincity": 137, "concept:buildingfeaturemadefrombuildingmaterial": 138, "concept:musicianinmusicartist": 139, "concept:ceoof": 140, "concept:chemicalistypeofchemical": 141, "concept:drugworkedonbyagent": 142, "concept:citylocatedincountry": 143, "concept:citylocatedingeopoliticallocation": 144, "concept:cityliesonriver": 145, "concept:cityalsoknownas": 146, "concept:citylocatedinstate": 147, "concept:citycapitalofcountry": 148, "concept:clothingmadefromplant": 149, "concept:clothingtogowithclothing": 150, "concept:newspaperincity": 151, "concept:countryalsoknownas": 152, "concept:countrylocatedingeopoliticallocation": 153, "concept:countrycurrency": 154, "concept:teamplaysinleague": 155, "concept:teamalsoknownas": 156, "concept:directordirectedmovie": 157, "concept:emotionassociatedwithdisease": 158, "concept:fishservedwithfood": 159, "concept:plantincludeplant": 160, "concept:plantgrowinginplant": 161, "concept:plantrepresentemotion": 162, "concept:furniturefoundinroom": 163, "concept:teamplayssport": 164, "concept:teamplaysagainstteam": 165, "concept:hobbiessuchashobbies": 166, "concept:sportfansincountry": 167, "concept:sportschoolincountry": 168, "concept:sportusesequipment": 169, "concept:professionistypeofprofession": 170, "concept:professionusestool": 171, "concept:journalistwritesforpublication": 172, "concept:lakeinstate": 173, "concept:languageofcountry": 174, "concept:languageofuniversity": 175, "concept:musicianplaysinstrument": 176, "concept:mountaininstate": 177, "concept:museumincity": 178, "concept:musicartistgenre": 179, "concept:musicgenressuchasmusicgenres": 180, "concept:radiostationincity": 181, "concept:conceptprerequisiteof": 182, "concept:sporthassportsteamposition": 183, "concept:sportusesstadium": 184, "concept:sportsgamesport": 185, "concept:sportsgameteam": 186, "concept:sportsgamewinner": 187, "concept:leaguestadiums": 188, "concept:teamplaysincity": 189, "concept:teamwontrophy": 190, "concept:teamhomestadium": 191, "concept:statelocatedincountry": 192, "concept:statehascapital": 193, "concept:statelocatedingeopoliticallocation": 194, "concept:stateorprovinceisborderedbystateorprovince": 195, "concept:televisionstationincity": 196, "concept:televisionstationaffiliatedwith": 197, "concept:weaponssuchasweapons": 198, "concept:weaponmadeincountry": 199, "concept:academicprogramatuniversity_reverse": 200, "concept:proxyfor_reverse": 201, "concept:atdate_reverse": 202, "concept:subpartof_reverse": 203, "concept:academicfieldsuchasacademicfield_reverse": 204, "concept:academicfieldconcernssubject_reverse": 205, "concept:synonymfor_reverse": 206, "concept:mutualproxyfor_reverse": 207, "concept:ismultipleof_reverse": 208, "concept:istallerthan_reverse": 209, "concept:latitudelongitude_reverse": 210, "concept:atlocation_reverse": 211, "concept:actorstarredinmovie_reverse": 212, "concept:hasspouse_reverse": 213, "concept:agentinvolvedwithitem_reverse": 214, "concept:agentparticipatedinevent_reverse": 215, "concept:personchargedwithcrime_reverse": 216, "concept:personhasresidenceingeopoliticallocation_reverse": 217, "concept:agentcreated_reverse": 218, "concept:haswife_reverse": 219, "concept:persondiedincountry_reverse": 220, "concept:persondiedatage_reverse": 221, "concept:personbelongstoorganization_reverse": 222, "concept:personhasjobposition_reverse": 223, "concept:personalsoknownas_reverse": 224, "concept:worksfor_reverse": 225, "concept:agentcontributedtocreativework_reverse": 226, "concept:personleadsorganization_reverse": 227, "concept:agentcompeteswithagent_reverse": 228, "concept:agentactsinlocation_reverse": 229, "concept:agentcontrols_reverse": 230, "concept:topmemberoforganization_reverse": 231, "concept:hashusband_reverse": 232, "concept:personleadsgeopoliticalorganization_reverse": 233, "concept:personbornincity_reverse": 234, "concept:personborninlocation_reverse": 235, "concept:parentofperson_reverse": 236, "concept:agentcollaborateswithagent_reverse": 237, "concept:personhascitizenship_reverse": 238, "concept:persongraduatedfromuniversity_reverse": 239, "concept:persongraduatedschool_reverse": 240, "concept:organizationalsoknownas_reverse": 241, "concept:organizationterminatedperson_reverse": 242, "concept:objectfoundinscene_reverse": 243, "concept:objectpartofobject_reverse": 244, "concept:agriculturalproductgrowninlandscapefeatures_reverse": 245, "concept:foodcancausedisease_reverse": 246, "concept:agriculturalproductincludingagriculturalproduct_reverse": 247, "concept:agriculturalproductcontainchemical_reverse": 248, "concept:fooddecreasestheriskofdisease_reverse": 249, "concept:agriculturalproductcookedwithagriculturalproduct_reverse": 250, "concept:agriculturalproductcutintogeometricshape_reverse": 251, "concept:agriculturalproducttoattractinsect_reverse": 252, "concept:thinghascolor_reverse": 253, "concept:agriculturalproductcomingfromvertebrate_reverse": 254, "concept:agriculturalproductcamefromcountry_reverse": 255, "concept:animalistypeofanimal_reverse": 256, "concept:mammalsuchasmammal_reverse": 257, "concept:animaleatvegetable_reverse": 258, "concept:specializationof_reverse": 259, "concept:beveragemadefrombeverage_reverse": 260, "concept:beveragecontainsprotein_reverse": 261, "concept:agriculturalproductgrowinginstateorprovince_reverse": 262, "concept:arthropodcalledarthropod_reverse": 263, "concept:animaleatfood_reverse": 264, "concept:animalpreyson_reverse": 265, "concept:animaldevelopdisease_reverse": 266, "concept:thinghasshape_reverse": 267, "concept:animalsuchasfish_reverse": 268, "concept:airportincity_reverse": 269, "concept:buildinglocatedincity_reverse": 270, "concept:touristattractionsuchastouristattraction_reverse": 271, "concept:attractionofcity_reverse": 272, "concept:locationlocatedwithinlocation_reverse": 273, "concept:transportationincity_reverse": 274, "concept:animalthatfeedoninsect_reverse": 275, "concept:animalsuchasinvertebrate_reverse": 276, "concept:animalsuchasinsect_reverse": 277, "concept:invertebratefeedonfood_reverse": 278, "concept:arthropodandotherarthropod_reverse": 279, "concept:drugpossiblytreatsphysiologicalcondition_reverse": 280, "concept:hassibling_reverse": 281, "concept:visualartistartform_reverse": 282, "concept:arterycalledartery_reverse": 283, "concept:bodypartcontainsbodypart_reverse": 284, "concept:politicianrepresentslocation_reverse": 285, "concept:politicianusmemberofpoliticalgroup_reverse": 286, "concept:politicianusendorsedbypoliticianus_reverse": 287, "concept:politicianusholdsoffice_reverse": 288, "concept:politicianholdsoffice_reverse": 289, "concept:personmovedtostateorprovince_reverse": 290, "concept:athleteplayssport_reverse": 291, "concept:coachwontrophy_reverse": 292, "concept:athleteflyouttosportsteamposition_reverse": 293, "concept:athleteinjuredhisbodypart_reverse": 294, "concept:athleteplayssportsteamposition_reverse": 295, "concept:athleteplaysinleague_reverse": 296, "concept:athleteplaysforteam_reverse": 297, "concept:athleteledsportsteam_reverse": 298, "concept:athletehomestadium_reverse": 299, "concept:athletewinsawardtrophytournament_reverse": 300, "concept:athletebeatathlete_reverse": 301, "concept:coachesinleague_reverse": 302, "concept:agentbelongstoorganization_reverse": 303, "concept:fatherofperson_reverse": 304, "concept:coachesteam_reverse": 305, "concept:motherofperson_reverse": 306, "concept:riveremptiesintoriver_reverse": 307, "concept:hotelincity_reverse": 308, "concept:automobilemakerdealersincountry_reverse": 309, "concept:automakerproducesmodel_reverse": 310, "concept:automobilemakerdealersincity_reverse": 311, "concept:automobilemakercardealersinstateorprovince_reverse": 312, "concept:hasofficeincountry_reverse": 313, "concept:companyeconomicsector_reverse": 314, "concept:subpartoforganization_reverse": 315, "concept:acquired_reverse": 316, "concept:producesproduct_reverse": 317, "concept:competeswith_reverse": 318, "concept:headquarteredin_reverse": 319, "concept:companyalsoknownas_reverse": 320, "concept:organizationheadquarteredinstateorprovince_reverse": 321, "concept:organizationhiredperson_reverse": 322, "concept:hasofficeincity_reverse": 323, "concept:organizationheadquarteredincountry_reverse": 324, "concept:organizationdissolvedatdate_reverse": 325, "concept:organizationheadquarteredincity_reverse": 326, "concept:awardtrophytournamentisthechampionshipgameofthenationalsport_reverse": 327, "concept:bacteriaisthecausativeagentofphysiologicalcondition_reverse": 328, "concept:drughassideeffect_reverse": 329, "concept:bakedgoodservedwithbeverage_reverse": 330, "concept:organizationacronymhasname_reverse": 331, "concept:bankbankincountry_reverse": 332, "concept:bankboughtbank_reverse": 333, "concept:itemfoundinroom_reverse": 334, "concept:parkincity_reverse": 335, "concept:bookwriter_reverse": 336, "concept:stadiumlocatedincity_reverse": 337, "concept:buildingfeaturemadefrombuildingmaterial_reverse": 338, "concept:musicianinmusicartist_reverse": 339, "concept:ceoof_reverse": 340, "concept:chemicalistypeofchemical_reverse": 341, "concept:drugworkedonbyagent_reverse": 342, "concept:citylocatedincountry_reverse": 343, "concept:citylocatedingeopoliticallocation_reverse": 344, "concept:cityliesonriver_reverse": 345, "concept:cityalsoknownas_reverse": 346, "concept:citylocatedinstate_reverse": 347, "concept:citycapitalofcountry_reverse": 348, "concept:clothingmadefromplant_reverse": 349, "concept:clothingtogowithclothing_reverse": 350, "concept:newspaperincity_reverse": 351, "concept:countryalsoknownas_reverse": 352, "concept:countrylocatedingeopoliticallocation_reverse": 353, "concept:countrycurrency_reverse": 354, "concept:teamplaysinleague_reverse": 355, "concept:teamalsoknownas_reverse": 356, "concept:directordirectedmovie_reverse": 357, "concept:emotionassociatedwithdisease_reverse": 358, "concept:fishservedwithfood_reverse": 359, "concept:plantincludeplant_reverse": 360, "concept:plantgrowinginplant_reverse": 361, "concept:plantrepresentemotion_reverse": 362, "concept:furniturefoundinroom_reverse": 363, "concept:teamplayssport_reverse": 364, "concept:teamplaysagainstteam_reverse": 365, "concept:hobbiessuchashobbies_reverse": 366, "concept:sportfansincountry_reverse": 367, "concept:sportschoolincountry_reverse": 368, "concept:sportusesequipment_reverse": 369, "concept:professionistypeofprofession_reverse": 370, "concept:professionusestool_reverse": 371, "concept:journalistwritesforpublication_reverse": 372, "concept:lakeinstate_reverse": 373, "concept:languageofcountry_reverse": 374, "concept:languageofuniversity_reverse": 375, "concept:musicianplaysinstrument_reverse": 376, "concept:mountaininstate_reverse": 377, "concept:museumincity_reverse": 378, "concept:musicartistgenre_reverse": 379, "concept:musicgenressuchasmusicgenres_reverse": 380, "concept:radiostationincity_reverse": 381, "concept:conceptprerequisiteof_reverse": 382, "concept:sporthassportsteamposition_reverse": 383, "concept:sportusesstadium_reverse": 384, "concept:sportsgamesport_reverse": 385, "concept:sportsgameteam_reverse": 386, "concept:sportsgamewinner_reverse": 387, "concept:leaguestadiums_reverse": 388, "concept:teamplaysincity_reverse": 389, "concept:teamwontrophy_reverse": 390, "concept:teamhomestadium_reverse": 391, "concept:statelocatedincountry_reverse": 392, "concept:statehascapital_reverse": 393, "concept:statelocatedingeopoliticallocation_reverse": 394, "concept:stateorprovinceisborderedbystateorprovince_reverse": 395, "concept:televisionstationincity_reverse": 396, "concept:televisionstationaffiliatedwith_reverse": 397, "concept:weaponssuchasweapons_reverse": 398, "concept:weaponmadeincountry_reverse": 399}